fastapi_msal/__init__.py
fastapi_msal/_version.py
fastapi_msal/auth.py
fastapi_msal/py.typed
fastapi_msal/clients/__init__.py
fastapi_msal/clients/async_conf_client.py
fastapi_msal/core/__init__.py
fastapi_msal/core/msal_client_config.py
fastapi_msal/core/session_manager.py
fastapi_msal/core/utils.py
fastapi_msal/models/__init__.py
fastapi_msal/models/auth_code.py
fastapi_msal/models/auth_token.py
fastapi_msal/models/base_auth_model.py
fastapi_msal/models/common.py
fastapi_msal/models/id_token_claims.py
fastapi_msal/models/local_account.py
fastapi_msal/models/user_info.py
fastapi_msal/security/__init__.py
fastapi_msal/security/msal_auth_code_handler.py
fastapi_msal/security/msal_scheme.py
fastapi_msal-2.1.7.dist-info/METADATA
fastapi_msal-2.1.7.dist-info/WHEEL
fastapi_msal-2.1.7.dist-info/licenses/LICENSE
fastapi_msal-2.1.7.dist-info/RECORD
