Metadata-Version: 2.4
Name: fastapi_msal
Version: 2.1.7
Summary: FastAPI/MSAL - The MSAL (Microsoft Authentication Library) plugin for FastAPI!
Project-URL: Homepage, https://github.com/dudil/fastapi_msal
Project-URL: Documentation, https://github.com/dudil/fastapi_msal#readme
Project-URL: Issues, https://github.com/dudil/fastapi_msal/issues
Project-URL: Source, https://github.com/dudil/fastapi_msal
Author-email: Dudi Levy <4785835+dudil@users.noreply.github.com>
License-Expression: MIT
License-File: LICENSE
Keywords: AAD,FastAPI,MSAL,SSO,authentication,fastapi-middleware,fastapi-plugin,plugin
Classifier: Development Status :: 5 - Production/Stable
Classifier: Framework :: AsyncIO
Classifier: Intended Audience :: Developers
Classifier: Intended Audience :: Information Technology
Classifier: Intended Audience :: System Administrators
Classifier: License :: OSI Approved :: MIT License
Classifier: Programming Language :: Python :: 3.9
Classifier: Programming Language :: Python :: 3.10
Classifier: Programming Language :: Python :: 3.11
Classifier: Programming Language :: Python :: 3.12
Classifier: Topic :: Software Development
Classifier: Topic :: Software Development :: Libraries
Classifier: Topic :: Software Development :: Libraries :: Python Modules
Classifier: Typing :: Typed
Requires-Python: >=3.9
Requires-Dist: fastapi
Requires-Dist: msal
Requires-Dist: pydantic-settings>=2.0
Requires-Dist: pydantic>=2.4
Requires-Dist: starlette
Provides-Extra: dev
Requires-Dist: black; extra == 'dev'
Requires-Dist: httpx; extra == 'dev'
Requires-Dist: itsdangerous; extra == 'dev'
Requires-Dist: mypy; extra == 'dev'
Requires-Dist: pytest; extra == 'dev'
Requires-Dist: python-multipart; extra == 'dev'
Requires-Dist: ruff; extra == 'dev'
Provides-Extra: full
Requires-Dist: itsdangerous; extra == 'full'
Requires-Dist: python-multipart; extra == 'full'
